datapath/__init__.py
datapath/_pipe.py
datapath/_value.py
nice_datapath-0.0.1.dist-info/METADATA
nice_datapath-0.0.1.dist-info/WHEEL
nice_datapath-0.0.1.dist-info/top_level.txt
nice_datapath-0.0.1.dist-info/RECORD
