Metadata-Version: 2.1
Name: nice-datapath
Version: 0.0.1
Summary: easy data picker
Home-page: https://github.com/minusli/nice-datapath
Author: minusli
Author-email: minusli@foxmail.com
License: Apache License 2.0
Platform: UNKNOWN
Requires-Python: >=3
